selenium_utils_xmlangel/__init__.py
selenium_utils_xmlangel/compare_image.py
selenium_utils_xmlangel-0.0.4.dist-info/METADATA
selenium_utils_xmlangel-0.0.4.dist-info/WHEEL
selenium_utils_xmlangel-0.0.4.dist-info/top_level.txt
selenium_utils_xmlangel-0.0.4.dist-info/RECORD
